neurodesign/__init__.py
neurodesign/generate.py
neurodesign/geneticalgorithm.py
neurodesign/msequence.py
neurodesign/report.py
neurodesign/media/NeuroDes.png
neurodesign-0.1.6.dist-info/DESCRIPTION.rst
neurodesign-0.1.6.dist-info/METADATA
neurodesign-0.1.6.dist-info/RECORD
neurodesign-0.1.6.dist-info/WHEEL
neurodesign-0.1.6.dist-info/metadata.json
neurodesign-0.1.6.dist-info/top_level.txt
