Metadata-Version: 2.0
Name: neurodesign
Version: 0.1.6
Summary: Package for design optimisation for fMRI experiments
Home-page: UNKNOWN
Author: Joke Durnez
Author-email: joke.durnez@gmail.com
License: MIT
Platform: UNKNOWN
